web/__init__.py
web/cli.py
web/constants.py
web/core.py
web/routes.py
web/views.py
web/templates/index.html
1bead.org-0.0.11.dist-info/LICENSE
1bead.org-0.0.11.dist-info/METADATA
1bead.org-0.0.11.dist-info/WHEEL
1bead.org-0.0.11.dist-info/entry_points.txt
1bead.org-0.0.11.dist-info/top_level.txt
1bead.org-0.0.11.dist-info/RECORD
